file_upload_handler.py
mcp_document_parse-0.1.4.dist-info/licenses/LICENSE
mcp_document_parse-0.1.4.dist-info/METADATA
mcp_document_parse-0.1.4.dist-info/WHEEL
mcp_document_parse-0.1.4.dist-info/entry_points.txt
mcp_document_parse-0.1.4.dist-info/top_level.txt
mcp_document_parse-0.1.4.dist-info/RECORD
