Metadata-Version: 2.4
Name: mcp-document-parse
Version: 0.1.4
Summary: MCP provider for document parsing and conversion to Markdown
Author-email: Niutrans <tianfengning@niutrans.com>
License: MIT
Project-URL: Homepage, https://niutrans.com
Project-URL: Source, https://github.com/niutrans/mcp-document-parse
Keywords: mcp,document,parsing,markdown,pdf,word,excel,ppt
Classifier: Programming Language :: Python :: 3
Classifier: Programming Language :: Python :: 3.9
Classifier: Programming Language :: Python :: 3.10
Classifier: Programming Language :: Python :: 3.11
Classifier: Programming Language :: Python :: 3.12
Classifier: License :: OSI Approved :: MIT License
Classifier: Operating System :: OS Independent
Requires-Python: >=3.10
License-File: LICENSE
Requires-Dist: mcp[cli]>=1.21.0
Requires-Dist: requests>=2.31.0
Requires-Dist: tqdm>=4.60.0
Provides-Extra: dev
Requires-Dist: uv; extra == "dev"
Dynamic: license-file
